[
  {
    "name": "Australia",
    "countries": ["AU"],
    "states": []
  },
  {
    "name": "New Zealand",
    "countries": ["NZ"],
    "states": []
  },
  {
    "name": "UK",
    "countries": ["GB"],
    "states": []
  },
  {
    "name": "Canada_Alberta",
    "countries": ["CA"],
    "states": ["AB"]
  },
  {
    "name": "Canada_British Columbia",
    "countries": ["CA"],
    "states": ["BC"]
  },
  {
    "name": "Canada_Manitoba",
    "countries": ["CA"],
    "states": ["MB"]
  },
  {
    "name": "Canada_New Brunswick",
    "countries": ["CA"],
    "states": ["NB"]
  },
  {
    "name": "Canada_Newfoundland & Labrador",
    "countries": ["CA"],
    "states": ["NL"]
  },
  {
    "name": "Canada_Nova Scotia",
    "countries": ["CA"],
    "states": ["NS"]
  },
  {
    "name": "Canada_Northwest Territories",
    "countries": ["CA"],
    "states": ["NT"]
  },
  {
    "name": "Canada_Nunavut",
    "countries": ["CA"],
    "states": ["NU"]
  },
  {
    "name": "Canada_Ontario",
    "countries": ["CA"],
    "states": ["ON"]
  },
  {
    "name": "Canada_Prince Edward Island",
    "countries": ["CA"],
    "states": ["PE"]
  },
  {
    "name": "Canada_Quebec",
    "countries": ["CA"],
    "states": ["QC"]
  },
  {
    "name": "Canada_Saskatchewan",
    "countries": ["CA"],
    "states": ["SK"]
  },
  {
    "name": "Canada_Yukon",
    "countries": ["CA"],
    "states": ["YT"]
  },
  {
    "name": "Canada",
    "countries": ["CA"],
    "states": []
  },
  {
    "name": "Austria",
    "countries": ["AT"],
    "states": []
  },
  {
    "name": "Belgium",
    "countries": ["BE"],
    "states": []
  },
  {
    "name": "Bulgaria",
    "countries": ["BG"],
    "states": []
  },
  {
    "name": "Cyprus",
    "countries": ["CY"],
    "states": []
  },
  {
    "name": "Czech Republic",
    "countries": ["CZ"],
    "states": []
  },
  {
    "name": "Croatia",
    "countries": ["HR"],
    "states": []
  },
  {
    "name": "Denmark",
    "countries": ["DK"],
    "states": []
  },
  {
    "name": "Estonia",
    "countries": ["EE"],
    "states": []
  },
  {
    "name": "Finland",
    "countries": ["FI"],
    "states": []
  },
  {
    "name": "France",
    "countries": ["FR"],
    "states": []
  },
  {
    "name": "Germany",
    "countries": ["DE"],
    "states": []
  },
  {
    "name": "Greece",
    "countries": ["GR"],
    "states": []
  },
  {
    "name": "Hungary",
    "countries": ["HU"],
    "states": []
  },
  {
    "name": "Ireland",
    "countries": ["IE"],
    "states": []
  },
  {
    "name": "Italy",
    "countries": ["IT"],
    "states": []
  },
  {
    "name": "Latvia",
    "countries": ["LV"],
    "states": []
  },
  {
    "name": "Lithuania",
    "countries": ["LT"],
    "states": []
  },
  {
    "name": "Luxembourg",
    "countries": ["LU"],
    "states": []
  },
  {
    "name": "Malta",
    "countries": ["MT"],
    "states": []
  },
  {
    "name": "Netherlands",
    "countries": ["NL"],
    "states": []
  },
  {
    "name": "Poland",
    "countries": ["PL"],
    "states": []
  },
  {
    "name": "Portugal",
    "countries": ["PT"],
    "states": []
  },
  {
    "name": "Romania",
    "countries": ["RO"],
    "states": []
  },
  {
    "name": "Slovakia",
    "countries": ["SK"],
    "states": []
  },
  {
    "name": "Slovenia",
    "countries": ["SI"],
    "states": []
  },
  {
    "name": "Spain",
    "countries": ["ES"],
    "states": []
  },
  {
    "name": "Sweden",
    "countries": ["SE"],
    "states": []
  },
  {
    "name": "USA_Alaska",
    "countries": ["US"],
    "states": ["AK"]
  },
  {
    "name": "USA_Alabama",
    "countries": ["US"],
    "states": ["AL"]
  },
  {
    "name": "USA_Arkansas",
    "countries": ["US"],
    "states": ["AR"]
  },
  {
    "name": "USA_Arizona",
    "countries": ["US"],
    "states": ["AZ"]
  },
  {
    "name": "USA_California",
    "countries": ["US"],
    "states": ["CA"]
  },
  {
    "name": "USA_Colorado",
    "countries": ["US"],
    "states": ["CO"]
  },
  {
    "name": "USA_Connecticut",
    "countries": ["US"],
    "states": ["CT"]
  },
  {
    "name": "USA_Washington DC",
    "countries": ["US"],
    "states": ["DC"]
  },
  {
    "name": "USA_Delaware",
    "countries": ["US"],
    "states": ["DE"]
  },
  {
    "name": "USA_Florida",
    "countries": ["US"],
    "states": ["FL"]
  },
  {
    "name": "USA_Georgia",
    "countries": ["US"],
    "states": ["GA"]
  },
  {
    "name": "USA_Hawaii",
    "countries": ["US"],
    "states": ["HI"]
  },
  {
    "name": "USA_Iowa",
    "countries": ["US"],
    "states": ["IA"]
  },
  {
    "name": "USA_Idaho",
    "countries": ["US"],
    "states": ["ID"]
  },
  {
    "name": "USA_Illinois",
    "countries": ["US"],
    "states": ["IL"]
  },
  {
    "name": "USA_Indiana",
    "countries": ["US"],
    "states": ["IN"]
  },
  {
    "name": "USA_Kansas",
    "countries": ["US"],
    "states": ["KS"]
  },
  {
    "name": "USA_Kentucky",
    "countries": ["US"],
    "states": ["KY"]
  },
  {
    "name": "USA_Louisiana",
    "countries": ["US"],
    "states": ["LA"]
  },
  {
    "name": "USA_Massachusetts",
    "countries": ["US"],
    "states": ["MA"]
  },
  {
    "name": "USA_Maryland",
    "countries": ["US"],
    "states": ["MD"]
  },
  {
    "name": "USA_Maine",
    "countries": ["US"],
    "states": ["ME"]
  },
  {
    "name": "USA_Michigan",
    "countries": ["US"],
    "states": ["MI"]
  },
  {
    "name": "USA_Minnesota",
    "countries": ["US"],
    "states": ["MN"]
  },
  {
    "name": "USA_Missouri",
    "countries": ["US"],
    "states": ["MO"]
  },
  {
    "name": "USA_Mississippi",
    "countries": ["US"],
    "states": ["MS"]
  },
  {
    "name": "USA_Montana",
    "countries": ["US"],
    "states": ["MT"]
  },
  {
    "name": "USA_North Carolina",
    "countries": ["US"],
    "states": ["NC"]
  },
  {
    "name": "USA_North Dakota",
    "countries": ["US"],
    "states": ["ND"]
  },
  {
    "name": "USA_Nebraska",
    "countries": ["US"],
    "states": ["NE"]
  },
  {
    "name": "USA_New Hampshire",
    "countries": ["US"],
    "states": ["NH"]
  },
  {
    "name": "USA_New Jersey",
    "countries": ["US"],
    "states": ["NJ"]
  },
  {
    "name": "USA_New Mexico",
    "countries": ["US"],
    "states": ["NM"]
  },
  {
    "name": "USA_Nevada",
    "countries": ["US"],
    "states": ["NV"]
  },
  {
    "name": "USA_New York",
    "countries": ["US"],
    "states": ["NY"]
  },
  {
    "name": "USA_Ohio",
    "countries": ["US"],
    "states": ["OH"]
  },
  {
    "name": "USA_Oklahoma",
    "countries": ["US"],
    "states": ["OK"]
  },
  {
    "name": "USA_Oregon",
    "countries": ["US"],
    "states": ["OR"]
  },
  {
    "name": "USA_Pennsylvania",
    "countries": ["US"],
    "states": ["PA"]
  },
  {
    "name": "USA_Puerto Rico",
    "countries": ["US"],
    "states": ["PR"]
  },
  {
    "name": "USA_Rhode Island",
    "countries": ["US"],
    "states": ["RI"]
  },
  {
    "name": "USA_South Carolina",
    "countries": ["US"],
    "states": ["SC"]
  },
  {
    "name": "USA_South Dakota",
    "countries": ["US"],
    "states": ["SD"]
  },
  {
    "name": "USA_Tennessee",
    "countries": ["US"],
    "states": ["TN"]
  },
  {
    "name": "USA_Texas",
    "countries": ["US"],
    "states": ["TX"]
  },
  {
    "name": "USA_Utah",
    "countries": ["US"],
    "states": ["UT"]
  },
  {
    "name": "USA_Virginia",
    "countries": ["US"],
    "states": ["VA"]
  },
  {
    "name": "USA_Vermont",
    "countries": ["US"],
    "states": ["VT"]
  },
  {
    "name": "USA_Washington",
    "countries": ["US"],
    "states": ["WA"]
  },
  {
    "name": "USA_Wisconsin",
    "countries": ["US"],
    "states": ["WI"]
  },
  {
    "name": "USA_West Virginia",
    "countries": ["US"],
    "states": ["WV"]
  },
  {
    "name": "USA_Wyoming",
    "countries": ["US"],
    "states": ["WY"]
  },
  {
    "name": "USA",
    "countries": ["US"],
    "states": []
  },
  {
    "name": "REST_OF_THE_WORLD",
    "isDefault": true,
    "countries": [],
    "states": []
  }
]