{"fa-ambulance":"fa-ambulance.png","fa-anchor":"fa-anchor.png","fa-android":"fa-android.png","fa-angellist":"fa-angellist.png","fa-angle-down":"fa-angle-down.png","fa-angle-left":"fa-angle-left.png","fa-angle-right":"fa-angle-right.png","fa-angle-up":"fa-angle-up.png","fa-area-chart":"fa-area-chart.png","fa-arrow-circle-o-left":"fa-arrow-circle-o-left.png","fa-arrow-circle-o-right":"fa-arrow-circle-o-right.png","fa-arrows-alt":"fa-arrows-alt.png","fa-automobile":"fa-automobile.png","fa-balance-scale":"fa-balance-scale.png","fa-bank":"fa-bank.png","fa-bar-chart-o":"fa-bar-chart-o.png","fa-bar-chart":"fa-bar-chart.png","fa-bed":"fa-bed.png","fa-beer":"fa-beer.png","fa-behance":"fa-behance.png","fa-bell-o":"fa-bell-o.png","fa-bicycle":"fa-bicycle.png","fa-binoculars":"fa-binoculars.png","fa-birthday-cake":"fa-birthday-cake.png","fa-bitbucket-square":"fa-bitbucket-square.png","fa-bitbucket":"fa-bitbucket.png","fa-black-tie":"fa-black-tie.png","fa-bolt":"fa-bolt.png","fa-book":"fa-book.png","fa-bookmark-o":"fa-bookmark-o.png","fa-bookmark":"fa-bookmark.png","fa-briefcase":"fa-briefcase.png","fa-bug":"fa-bug.png","fa-building-o":"fa-building-o.png","fa-building":"fa-building.png","fa-bullhorn":"fa-bullhorn.png","fa-bullseye":"fa-bullseye.png","fa-bus":"fa-bus.png","fa-buysellads":"fa-buysellads.png","fa-calculator":"fa-calculator.png","fa-calendar-check-o":"fa-calendar-check-o.png","fa-calendar-minus-o":"fa-calendar-minus-o.png","fa-calendar-o":"fa-calendar-o.png","fa-calendar-plus-o":"fa-calendar-plus-o.png","fa-calendar-times-o":"fa-calendar-times-o.png","fa-calendar":"fa-calendar.png","fa-camera-retro":"fa-camera-retro.png","fa-camera":"fa-camera.png","fa-car":"fa-car.png","fa-caret-down":"fa-caret-down.png","fa-caret-left":"fa-caret-left.png","fa-caret-right":"fa-caret-right.png","fa-caret-up":"fa-caret-up.png","fa-cart-arrow-down":"fa-cart-arrow-down.png","fa-cc-amex":"fa-cc-amex.png","fa-cc-mastercard":"fa-cc-mastercard.png","fa-cc-visa":"fa-cc-visa.png","fa-cc":"fa-cc.png","fa-certificate":"fa-certificate.png","fa-chain-broken":"fa-chain-broken.png","fa-check-circle-o":"fa-check-circle-o.png","fa-chevron-down":"fa-chevron-down.png","fa-chevron-left":"fa-chevron-left.png","fa-chevron-right":"fa-chevron-right.png","fa-chevron-up":"fa-chevron-up.png","fa-circle-o-notch":"fa-circle-o-notch.png","fa-circle-thin":"fa-circle-thin.png","fa-clipboard":"fa-clipboard.png","fa-clock-o":"fa-clock-o.png","fa-clone":"fa-clone.png","fa-close":"fa-close.png","fa-cloud-download":"fa-cloud-download.png","fa-cloud-upload":"fa-cloud-upload.png","fa-cny":"fa-cny.png","fa-code-fork":"fa-code-fork.png","fa-code":"fa-code.png","fa-codepen":"fa-codepen.png","fa-columns":"fa-columns.png","fa-comment-o":"fa-comment-o.png","fa-commenting":"fa-commenting.png","fa-comments-o":"fa-comments-o.png","fa-compass":"fa-compass.png","fa-compress":"fa-compress.png","fa-connectdevelop":"fa-connectdevelop.png","fa-contao":"fa-contao.png","fa-copy":"fa-copy.png","fa-copyright":"fa-copyright.png","fa-creative-commons":"fa-creative-commons.png","fa-credit-card":"fa-credit-card.png","fa-crop":"fa-crop.png","fa-crosshairs":"fa-crosshairs.png","fa-css3":"fa-css3.png","fa-cube":"fa-cube.png","fa-cut":"fa-cut.png","fa-cutlery":"fa-cutlery.png","fa-dashboard":"fa-dashboard.png","fa-database":"fa-database.png","fa-desktop":"fa-desktop.png","fa-diamond":"fa-diamond.png","fa-dollar":"fa-dollar.png","fa-dropbox":"fa-dropbox.png","fa-ellipsis-h":"fa-ellipsis-h.png","fa-ellipsis-v":"fa-ellipsis-v.png","fa-envelope-o":"fa-envelope-o.png","fa-envelope-square":"fa-envelope-square.png","fa-envelope":"fa-envelope.png","fa-eraser":"fa-eraser.png","fa-external-link":"fa-external-link.png","fa-eye-slash":"fa-eye-slash.png","fa-eyedropper":"fa-eyedropper.png","fa-fax":"fa-fax.png","fa-feed":"fa-feed.png","fa-file-archive-o":"fa-file-archive-o.png","fa-file-code-o":"fa-file-code-o.png","fa-file-o":"fa-file-o.png","fa-file-powerpoint-o":"fa-file-powerpoint-o.png","fa-file-text-o":"fa-file-text-o.png","fa-files-o":"fa-files-o.png","fa-film":"fa-film.png","fa-filter":"fa-filter.png","fa-fire-extinguisher":"fa-fire-extinguisher.png","fa-fire":"fa-fire.png","fa-flag-o":"fa-flag-o.png","fa-floppy-o":"fa-floppy-o.png","fa-folder-o":"fa-folder-o.png","fa-folder-open-o":"fa-folder-open-o.png","fa-font":"fa-font.png","icon-adjustments":"icon-adjustments.png","icon-alarmclock":"icon-alarmclock.png","icon-anchor":"icon-anchor.png","icon-aperture":"icon-aperture.png","icon-attachment":"icon-attachment.png","icon-bargraph":"icon-bargraph.png","icon-basket":"icon-basket.png","icon-beaker":"icon-beaker.png","icon-bike":"icon-bike.png","icon-book-open":"icon-book-open.png","icon-briefcase":"icon-briefcase.png","icon-browser":"icon-browser.png","icon-calendar":"icon-calendar.png","icon-camera":"icon-camera.png","icon-caution":"icon-caution.png","icon-chat":"icon-chat.png","icon-circle-compass":"icon-circle-compass.png","icon-clipboard":"icon-clipboard.png","icon-clock":"icon-clock.png","icon-cloud":"icon-cloud.png","icon-compass":"icon-compass.png","icon-desktop":"icon-desktop.png","icon-dial":"icon-dial.png","icon-document":"icon-document.png","icon-documents":"icon-documents.png","icon-download":"icon-download.png","icon-dribbble":"icon-dribbble.png","icon-edit":"icon-edit.png","icon-envelope":"icon-envelope.png","icon-expand":"icon-expand.png","icon-facebook":"icon-facebook.png","icon-flag":"icon-flag.png","icon-focus":"icon-focus.png","icon-gears":"icon-gears.png","icon-genius":"icon-genius.png","icon-gift":"icon-gift.png","icon-global":"icon-global.png","icon-globe":"icon-globe.png","icon-googleplus":"icon-googleplus.png","icon-grid":"icon-grid.png","icon-happy":"icon-happy.png","icon-hazardous":"icon-hazardous.png","icon-heart":"icon-heart.png","icon-hotairballoon":"icon-hotairballoon.png","icon-hourglass":"icon-hourglass.png","icon-key":"icon-key.png","icon-laptop":"icon-laptop.png","icon-layers":"icon-layers.png","icon-lifesaver":"icon-lifesaver.png","icon-lightbulb":"icon-lightbulb.png","icon-linegraph":"icon-linegraph.png","icon-linkedin":"icon-linkedin.png","icon-lock":"icon-lock.png","icon-magnifying-glass":"icon-magnifying-glass.png","icon-map-pin":"icon-map-pin.png","icon-map":"icon-map.png","icon-megaphone":"icon-megaphone.png","icon-mic":"icon-mic.png","icon-mobile":"icon-mobile.png","icon-newspaper":"icon-newspaper.png","icon-notebook":"icon-notebook.png","icon-paintbrush":"icon-paintbrush.png","icon-paperclip":"icon-paperclip.png","icon-pencil":"icon-pencil.png","icon-phone":"icon-phone.png","icon-picture":"icon-picture.png","icon-pictures":"icon-pictures.png","icon-piechart":"icon-piechart.png","icon-presentation":"icon-presentation.png","icon-pricetags":"icon-pricetags.png","icon-printer":"icon-printer.png","icon-profile-female":"icon-profile-female.png","icon-profile-male":"icon-profile-male.png","icon-puzzle":"icon-puzzle.png","icon-quote":"icon-quote.png","icon-recycle":"icon-recycle.png","icon-refresh":"icon-refresh.png","icon-ribbon":"icon-ribbon.png","icon-rss":"icon-rss.png","icon-sad":"icon-sad.png","icon-scissors":"icon-scissors.png","icon-scope":"icon-scope.png","icon-search":"icon-search.png","icon-shield":"icon-shield.png","icon-speedometer":"icon-speedometer.png","icon-strategy":"icon-strategy.png","icon-streetsign":"icon-streetsign.png","icon-tablet":"icon-tablet.png","icon-target":"icon-target.png","icon-telescope":"icon-telescope.png","icon-toolbox":"icon-toolbox.png","icon-tools-2":"icon-tools-2.png","icon-tools":"icon-tools.png","icon-trophy":"icon-trophy.png","icon-tumblr":"icon-tumblr.png","icon-twitter":"icon-twitter.png","icon-upload":"icon-upload.png","icon-video":"icon-video.png","icon-wallet":"icon-wallet.png","icon-wine":"icon-wine.png"}